apis_core/__init__.py
apis_core/urls.py
apis_core/apis_entities/__init__.py
apis_core/apis_entities/abc.py
apis_core/apis_entities/api_views.py
apis_core/apis_entities/apps.py
apis_core/apis_entities/featureCodes_en.txt
apis_core/apis_entities/fields.py
apis_core/apis_entities/filtersets.py
apis_core/apis_entities/forms.py
apis_core/apis_entities/models.py
apis_core/apis_entities/serializers.py
apis_core/apis_entities/urls.py
apis_core/apis_entities/utils.py
apis_core/apis_entities/views.py
apis_core/apis_entities/widgets.py
apis_core/apis_entities/locale/de/LC_MESSAGES/django.mo
apis_core/apis_entities/locale/de/LC_MESSAGES/django.po
apis_core/apis_entities/migrations/0001_initial.py
apis_core/apis_entities/migrations/0002_remove_tempentityclass_text.py
apis_core/apis_entities/migrations/0003_remove_tempentityclass_source.py
apis_core/apis_entities/migrations/0004_delete_tempentityclass.py
apis_core/apis_entities/migrations/__init__.py
apis_core/apis_entities/static/css/E53_Place_popover.css
apis_core/apis_entities/static/css/apis_entities.css
apis_core/apis_entities/static/js/E53_Place_map.js
apis_core/apis_entities/static/js/E53_Place_popover.js
apis_core/apis_entities/static/js/apis_entities.js
apis_core/apis_entities/static/js/placelookup.js
apis_core/apis_entities/templates/base.html
apis_core/apis_entities/templates/apis_core/apis_entities/abstractentity.html
apis_core/apis_entities/templates/apis_core/apis_entities/abstractentity_detail.html
apis_core/apis_entities/templates/apis_core/apis_entities/abstractentity_form.html
apis_core/apis_entities/templates/apis_core/apis_entities/e53_place_autocomplete_result.html
apis_core/apis_entities/templates/apis_core/apis_entities/e53_place_detail.html
apis_core/apis_entities/templates/apis_core/apis_entities/e53_place_list.html
apis_core/apis_entities/templates/apis_core/apis_entities/e53_place_map.html
apis_core/apis_entities/templates/apis_entities/partials/entity_actions_nav.html
apis_core_rdf-0.59.0.dist-info/METADATA
apis_core_rdf-0.59.0.dist-info/WHEEL
apis_core_rdf-0.59.0.dist-info/licenses/LICENSE.txt
apis_core_rdf-0.59.0.dist-info/RECORD
