Metadata-Version: 2.4
Name: apis-core-rdf
Version: 0.59.0
Summary: Base package for the APIS framework
Author-email: Matthias Schlögl <matthias.schloegl@oeaw.ac.at>, Birger Schacht <birger.schacht@oeaw.ac.at>, K Kollmann <dev-kk@oeaw.ac.at>, Saranya Balasubramanian <saranya.balasubramanian@oeaw.ac.at>
License-Expression: MIT
License-File: LICENSE.txt
Requires-Python: >=3.13
Requires-Dist: acdh-arche-assets<=4.0,>=3.21.1
Requires-Dist: crispy-bootstrap5>=2024.10
Requires-Dist: django-autocomplete-light<3.13.0,>=3.9.4
Requires-Dist: django-crispy-forms<3.0,>=2
Requires-Dist: django-crum<8.0,>=0.7.9
Requires-Dist: django-filter>=24.3
Requires-Dist: django-model-utils<6.0.0,>=4.1.1
Requires-Dist: django-simple-history>=3.6
Requires-Dist: django-tables2<3.0,>=2.3.3
Requires-Dist: django>=5.2
Requires-Dist: djangorestframework<4.0,>=3.14.0
Requires-Dist: drf-spectacular<0.30.0,>=0.26.1
Requires-Dist: httpx>=0.28.1
Requires-Dist: pydot<5.0,>=3.0.2
Requires-Dist: rdflib<8.0.0,>=6.0.2
Requires-Dist: tablib<=4.0,>=3.8.0
